nk256.py
nk256-1.0.0.dist-info/LICENSE
nk256-1.0.0.dist-info/METADATA
nk256-1.0.0.dist-info/WHEEL
nk256-1.0.0.dist-info/top_level.txt
nk256-1.0.0.dist-info/RECORD
