Metadata-Version: 2.2
Name: nk256
Version: 1.0.0
Summary: Unicode-based Base-256,000 numeral encoding system.
Home-page: https://github.com/dzbuit/nk256
Author: blueradiance
Author-email: none@example.com
Classifier: Programming Language :: Python :: 3
Classifier: License :: Other/Proprietary License
Classifier: Operating System :: OS Independent
Requires-Python: >=3.6
License-File: LICENSE
Dynamic: author
Dynamic: author-email
Dynamic: classifier
Dynamic: description
Dynamic: description-content-type
Dynamic: home-page
Dynamic: requires-python
Dynamic: summary
